{"type":"FeatureCollection","metadata":{"name":"Импорт из «Точки ОП и УМВД СПб - Лист4.csv»","creator":"Yandex Map Constructor"},"features":[{"type":"Feature","id":0,"geometry":{"type":"Point","coordinates":[39.206282,51.65842]},"properties":{"description":"394006, Воронеж, ул. Володарского, 39","iconCaption":"ГУ","marker-color":"#1e98ff"}},{"type":"Feature","id":1,"geometry":{"type":"Point","coordinates":[39.186132,51.652316]},"properties":{"description":"394006, Воронеж, ул. Краснознаменная,16","iconCaption":"УВ","marker-color":"#1e98ff"}},{"type":"Feature","id":2,"geometry":{"type":"Point","coordinates":[39.212389,51.68327]},"properties":{"description":"394061, Воронеж, ул. Транспортная, 1","iconCaption":"ЮВТ","marker-color":"#1e98ff"}},{"type":"Feature","id":3,"geometry":{"type":"Point","coordinates":[39.186132,51.652316]},"properties":{"description":"394006, Воронеж, ул. Краснознаменная,16","iconCaption":"ДВ","marker-color":"#1e98ff"}},{"type":"Feature","id":4,"geometry":{"type":"Point","coordinates":[39.273917,51.713575]},"properties":{"description":"394010, Воронеж, ул. Богдана Хмельницкого, 60а","iconCaption":"1","marker-color":"#1e98ff"}},{"type":"Feature","id":5,"geometry":{"type":"Point","coordinates":[39.18281,51.690867]},"properties":{"description":"394026, Воронеж, Московский пр., 13","iconCaption":"2","marker-color":"#1e98ff"}},{"type":"Feature","id":6,"geometry":{"type":"Point","coordinates":[39.244477,51.647612]},"properties":{"description":"394004, Воронеж, ул. Ленинградская, 31Б","iconCaption":"3","marker-color":"#1e98ff"}},{"type":"Feature","id":7,"geometry":{"type":"Point","coordinates":[39.140574,51.700391]},"properties":{"description":"394088, Воронеж, ул. Хользунова 123а","iconCaption":"4","marker-color":"#1e98ff"}},{"type":"Feature","id":8,"geometry":{"type":"Point","coordinates":[39.144499,51.653791]},"properties":{"description":"394051, Воронеж, ул. Маршака, 6А","iconCaption":"5","marker-color":"#1e98ff"}},{"type":"Feature","id":9,"geometry":{"type":"Point","coordinates":[39.206576,51.673521]},"properties":{"description":"394000, Воронеж, ул. Чайковского д.3","iconCaption":"6","marker-color":"#1e98ff"}},{"type":"Feature","id":10,"geometry":{"type":"Point","coordinates":[39.250307,51.612219]},"properties":{"description":"394008, Воронеж, ул. Волго-Донская, 20","iconCaption":"7","marker-color":"#1e98ff"}},{"type":"Feature","id":11,"geometry":{"type":"Point","coordinates":[39.187181,51.678463]},"properties":{"description":"394026, Воронеж, ул. Свердлова, д. 5д","iconCaption":"ДТВ","marker-color":"#1e98ff"}},{"type":"Feature","id":12,"geometry":{"type":"Point","coordinates":[39.177122,51.671312]},"properties":{"description":"ж/д станция Воронеж-Курский","iconCaption":"ЛП1","marker-color":"#1e98ff"}},{"type":"Feature","id":13,"geometry":{"type":"Point","coordinates":[39.25896,51.64014]},"properties":{"description":"ж/д станция Придача","iconCaption":"ЛП2","marker-color":"#1e98ff"}},{"type":"Feature","id":14,"geometry":{"type":"Point","coordinates":[39.266869,51.728422]},"properties":{"description":"ж/д станция Отрожка","iconCaption":"ЛП3","marker-color":"#1e98ff"}},{"type":"Feature","id":15,"geometry":{"type":"Point","coordinates":[39.22536,51.812537]},"properties":{"description":"394025, Воронеж, аэропорт Чертовицкое","iconCaption":"ЛТВ","marker-color":"#1e98ff"}}]}